django_hybrid_attributes/__init__.py
django_hybrid_attributes/core.py
django_hybrid_attributes/decorators.py
django_hybrid_attributes/managers.py
django_hybrid_attributes/test_utils.py
django_hybrid_attributes-0.1.0.dist-info/LICENSE
django_hybrid_attributes-0.1.0.dist-info/METADATA
django_hybrid_attributes-0.1.0.dist-info/WHEEL
django_hybrid_attributes-0.1.0.dist-info/top_level.txt
django_hybrid_attributes-0.1.0.dist-info/RECORD
