Metadata-Version: 2.1
Name: django-hybrid-attributes
Version: 0.1.0
Summary: A Django plugin for mimicking the power of SQLAlchemy hybrid_property and hybrid_method
Home-page: UNKNOWN
Author: Filipe Waitman
Author-email: filwaitman@gmail.com
License: MIT
Project-URL: Source, https://github.com/filwaitman/django-hybrid-attributes
Platform: UNKNOWN
Classifier: Development Status :: 4 - Beta
Classifier: Environment :: Web Environment
Classifier: Framework :: Django
Classifier: Framework :: Django :: 1.11
Classifier: Framework :: Django :: 2.0
Classifier: Framework :: Django :: 2.1
Classifier: Framework :: Django :: 2.2
Classifier: Framework :: Django :: 3.0
Classifier: Intended Audience :: Developers
Classifier: License :: OSI Approved :: MIT License
Classifier: Operating System :: OS Independent
Classifier: Programming Language :: Python
Classifier: Programming Language :: Python :: 3
Classifier: Programming Language :: Python :: 3.6
Classifier: Programming Language :: Python :: 3.7
Classifier: Programming Language :: Python :: 3.8
